netunicorn/director/infrastructure/connectors/__init__.py
netunicorn/director/infrastructure/connectors/ssh_connector.py
netunicorn_connector_ssh-0.0.2.dist-info/LICENSE
netunicorn_connector_ssh-0.0.2.dist-info/METADATA
netunicorn_connector_ssh-0.0.2.dist-info/WHEEL
netunicorn_connector_ssh-0.0.2.dist-info/top_level.txt
netunicorn_connector_ssh-0.0.2.dist-info/RECORD
